agent/__init__.py
agent/__main__.py
agent/agent.py
agent/config.py
agent/containers.py
agent/json_message_converter.py
agent/logger.py
agent/message_converter.py
agent/mqtt.py
agent/schemas.py
agent/vitals.py
agent/ros/__init__.py
agent/ros/humble.py
airbotics_agent-2023.8.14.dist-info/LICENSE
airbotics_agent-2023.8.14.dist-info/METADATA
airbotics_agent-2023.8.14.dist-info/NOTICE
airbotics_agent-2023.8.14.dist-info/WHEEL
airbotics_agent-2023.8.14.dist-info/entry_points.txt
airbotics_agent-2023.8.14.dist-info/top_level.txt
airbotics_agent-2023.8.14.dist-info/RECORD
