Metadata-Version: 2.1
Name: airbotics-agent
Version: 2023.8.14
Summary: The Airbotics cloud robotics agent
Author-email: "Airbotics Inc." <admin@airbotics.io>
License: 
Project-URL: Homepage, https://github.com/Airbotics
Keywords: airbotics,agent,robotics,ros
Classifier: License :: OSI Approved :: Apache Software License
Classifier: Programming Language :: Python :: 3
Requires-Python: >=3.7
License-File: LICENSE
License-File: NOTICE
Requires-Dist: python-daemon >=2.3.0
Requires-Dist: PyYAML >=6.0
Requires-Dist: docker >=5.0.3
Requires-Dist: paho-mqtt >=1.6.1
Requires-Dist: requests >=2.27.1
Requires-Dist: backoff >=2.0.1
Requires-Dist: jsonschema >=4.6.0
Requires-Dist: pyfiglet >=0.8.post1
Requires-Dist: numpy >=1.25.0
Requires-Dist: toml >=0.10.2
Requires-Dist: distro >=1.7.0
Requires-Dist: psutil >=5.9.5
